pymousekey/__init__.py
pymousekey-1.3.3.dist-info/METADATA
pymousekey-1.3.3.dist-info/WHEEL
pymousekey-1.3.3.dist-info/top_level.txt
pymousekey-1.3.3.dist-info/RECORD
