Metadata-Version: 2.4
Name: PyMouseKey
Version: 1.3.3
Summary: A python package for handling keyboard and mouse inputs
Author: Chasss
Dynamic: author
Dynamic: description
Dynamic: description-content-type
Dynamic: summary
